django_api_log/__init__.py
django_api_log/admin.py
django_api_log/apps.py
django_api_log/middleware.py
django_api_log/models.py
django_api_log/settings.py
django_api_log/tests.py
django_api_log/urls.py
django_api_log/views.py
django_api_log/migrations/0001_initial.py
django_api_log/migrations/0002_auto_20170503_1700.py
django_api_log/migrations/0003_apilog_django_error_page.py
django_api_log/migrations/__init__.py
django_api_log-0.2.3.dist-info/DESCRIPTION.rst
django_api_log-0.2.3.dist-info/METADATA
django_api_log-0.2.3.dist-info/RECORD
django_api_log-0.2.3.dist-info/WHEEL
django_api_log-0.2.3.dist-info/metadata.json
django_api_log-0.2.3.dist-info/top_level.txt
