Metadata-Version: 2.0
Name: django-api-log
Version: 0.2.3
Summary: Django reusable app for record request/response information to database for alert and audit.
Home-page: https://github.com/MythRen/django-api-log
Author: Myth
Author-email: belongmyth@163.com
License: BSD
Platform: UNKNOWN
